{
  "acquisition_instrument_vendor": {
    "Thermo": "Thermo Fisher Scientific",
    "Thermo Fisher": "Thermo Fisher Scientific",
    "Thermo Scientific": "Thermo Fisher Scientific",
    "Carl Zeiss Microscopy": "Zeiss Microscopy",
    "Bruker Daltonics": "Bruker",
    "ThermoFisher": "Thermo Fisher Scientific",
    "Fluidigm": "Standard BioTools (Fluidigm)",
    "Zeiss": "Zeiss Microscopy",
    "ThermoFisher Scientific": "Thermo Fisher Scientific",
    "Illumina ": "Illumina",
    "Waters Corp.": "Waters"
  }
}
